foundry_etl_sdk/__init__.py
foundry_etl_sdk/enums/__init__.py
foundry_etl_sdk/enums/insertion_mode.py
foundry_etl_sdk/objects/__init__.py
foundry_etl_sdk/objects/categories.py
foundry_etl_sdk/objects/company.py
foundry_etl_sdk/objects/data_points.py
foundry_etl_sdk/objects/datapoint_manager.py
foundry_etl_sdk/objects/dates.py
foundry_etl_sdk/objects/not_for_sale_flag.py
foundry_etl_sdk/objects/price_discounts.py
foundry_etl_sdk/objects/products.py
foundry_etl_sdk/objects/regions.py
foundry_etl_sdk/objects/sales.py
foundry_etl_sdk/objects/skus.py
foundry_etl_sdk/objects/stores.py
foundry_etl_sdk/objects/table_manager.py
foundry_etl_sdk/objects/time_region_features.py
foundry_etl_sdk/objects/time_store_features.py
foundry_etl_sdk/pipeline/__init__.py
foundry_etl_sdk/pipeline/base_etl_transformer.py
foundry_etl_sdk/pipeline/data_loader.py
foundry_etl_sdk/pipeline/database_manager.py
foundry_etl_sdk-0.1.10.dist-info/METADATA
foundry_etl_sdk-0.1.10.dist-info/WHEEL
foundry_etl_sdk-0.1.10.dist-info/top_level.txt
foundry_etl_sdk-0.1.10.dist-info/RECORD
